{
  "port": "EZMESURE_PORT",
  "mongo": {
    "port": "EZMESURE_MONGO_PORT",
    "host": "EZMESURE_MONGO_HOST",
    "db": "EZMESURE_MONGO_DB"
  },
  "elasticsearch": {
    "port": "EZMESURE_ELASTIC_PORT",
    "host": "EZMESURE_ELASTIC_HOST",
    "user": "EZMESURE_ELASTIC_USER",
    "password": "ELASTICSEARCH_PASSWORD",
    "apiVersion": "EZMESURE_ELASTIC_VERSION"
  },
  "kibana": {
    "username": "KIBANA_USERNAME",
    "password": "KIBANA_PASSWORD",
    "port": "EZMESURE_KIBANA_PORT",
    "host": "EZMESURE_KIBANA_HOST"
  },
  "smtp": {
    "host": "EZMESURE_SMTP_HOST",
    "port": "EZMESURE_SMTP_PORT",
    "secure": { "__name": "EZMESURE_SMTP_SECURE", "__format": "boolean" },
    "ignoreTLS": { "__name": "EZMESURE_SMTP_IGNORE_TLS", "__format": "boolean" },
    "tls": {
      "rejectUnauthorized": { "__name": "EZMESURE_SMTP_REJECT_UNAUTHORIZED", "__format": "boolean" }
    }
  },
  "notifications": {
    "cron": "EZMESURE_NOTIFICATIONS_CRON",
    "sender": "EZMESURE_NOTIFICATIONS_SENDER",
    "recipients": "EZMESURE_NOTIFICATIONS_RECIPIENTS",
    "sendEmptyActivity": { "__name": "EZMESURE_SEND_EMPTY_ACTIVITY", "__format": "boolean" }
  },
  "auth": {
    "secret": "EZMESURE_AUTH_SECRET",
    "cookie": "EZMESURE_AUTH_COOKIE"
  },
  "admin": {
    "username": "EZMESURE_ADMIN_USERNAME",
    "password": "EZMESURE_ADMIN_PASSWORD"
  },
  "storage": {
    "path": "EZMESURE_STORAGE_PATH"
  },
  "depositors": {
    "index": "EZMESURE_DEPOSITORS_INDEX",
    "spreadsheetId": "EZMESURE_DEPOSITORS_SPREADSHEET",
    "cron": "EZMESURE_DEPOSITORS_CRON"
  },
  "reportingActivityIndex": "REPORTING_ACTIVITY_INDEX",
  "reportingIndex": "REPORTING_INDEX",
  "cypher": {
    "secret": "EZMESURE_ENCRYPTION_SECRET"
  },
  "appName": "EZMESURE_APP_NAME"
}
